aliyun_ddns/__init__.py
aliyun_ddns/config.py
aliyun_ddns/ddns.py
aliyun_ddns/record.py
aliyun_ddns/utils.py
aliyun_ddns/yunresolver.py
aliyun_ddns_client-0.4.dist-info/METADATA
aliyun_ddns_client-0.4.dist-info/WHEEL
aliyun_ddns_client-0.4.dist-info/entry_points.txt
aliyun_ddns_client-0.4.dist-info/top_level.txt
aliyun_ddns_client-0.4.dist-info/zip-safe
aliyun_ddns_client-0.4.dist-info/RECORD
