Metadata-Version: 2.1
Name: aliyun-ddns-client
Version: 0.4
Summary: DDNS client for aliyun
Home-page: UNKNOWN
License: UNKNOWN
Platform: any
Requires-Dist: requests
